LICENSE
README.md
setup.cfg
setup.py
disttf/__init__.py
disttf/activate.py
disttf/asym_activate.py
disttf/box_activate.py
disttf/mixture.py
disttf/motio.py
disttf/multidim_activate.py
disttf/nonlinearity.py
disttf/recombine.py
disttf/scale.py
disttf/seperate.py
disttf/split.py
disttf.egg-info/PKG-INFO
disttf.egg-info/SOURCES.txt
disttf.egg-info/dependency_links.txt
disttf.egg-info/requires.txt
disttf.egg-info/top_level.txt