Metadata-Version: 2.1
Name: disttf
Version: 0.2.6
Summary: Python module providing arbitrary density distribution fit layers for tensorflow
Home-page: https://github.com/psorus/disttf
Download-URL: https://github.com/psorus/disttf/archive/v_01.tar.gz
Author: Simon Klüttermann
Author-email: Simon.Kluettermann@cs.tu-dortmund.de
License: apache-2.0
Keywords: ANOMALY DETECTION,OUTLIER DETECTION,TENSORFLOW,DENSITY,DENSITY FITTING
Platform: UNKNOWN
Classifier: Development Status :: 3 - Alpha
Classifier: Intended Audience :: Science/Research
Classifier: Topic :: Software Development :: Build Tools
Classifier: License :: OSI Approved :: Apache Software License
Classifier: Programming Language :: Python :: 3
Classifier: Programming Language :: Python :: 3.6
Classifier: Programming Language :: Python :: 3.7
Classifier: Programming Language :: Python :: 3.8
Classifier: Programming Language :: Python :: 3.9
Classifier: Programming Language :: Python :: 3.10
License-File: LICENSE
